{
  "version": 1,
  "serviceConfiguration": {
    "serviceName": "AppSync",
    "defaultAuthType": {
      "mode": "API_KEY",
      "keyDescription": "api key description",
      "expirationTime": 30
    },
    "additionalAuthTypes": [
      {
        "mode": "AWS_IAM"
      }
    ],
    "conflictResolution": {
      "defaultResolutionStrategy": {
        "type": "AUTOMERGE"
      }
    },
    "apiName": "kazu",
    "gqlSchemaPath": "/tmp/amplify-2fcaa100-fbef-43ab-805c-5564739be8e9/amplify/backend/api/kazu/schema.graphql"
  }
}